pip_change_repo/__init__.py
pip_change_repo/__main__.py
pip_change_repo/_cli.py
pip_change_repo-0.0.2.dist-info/METADATA
pip_change_repo-0.0.2.dist-info/WHEEL
pip_change_repo-0.0.2.dist-info/entry_points.txt
pip_change_repo-0.0.2.dist-info/top_level.txt
pip_change_repo-0.0.2.dist-info/RECORD
